README.md
setup.py
bin/dispatcher
dispatch/__init__.py
dispatch/core.py
dispatch/schedules.py
dispatch/utils.py
dispatch_reactor.egg-info/PKG-INFO
dispatch_reactor.egg-info/SOURCES.txt
dispatch_reactor.egg-info/dependency_links.txt
dispatch_reactor.egg-info/top_level.txt