Metadata-Version: 2.1
Name: dispatch-reactor
Version: 2.1.0
Summary: Module for dispatching jobs and timed operations
Home-page: https://github.com/jdotpy/dispatch
Author: KJ
Author-email: jdotpy@users.noreply.github.com
License: UNKNOWN
Download-URL: https://github.com/jdotpy/dispatch/tarball/master
Keywords: tools
Platform: UNKNOWN
Classifier: Programming Language :: Python :: 3
